pOrgz/__init__.py
pOrgz/api/SQLite3.py
pOrgz/api/__init__.py
pOrgz/api/_decorator.py
pOrgz/api/base.py
pOrgz/api/config.py
pOrgz/commons/SQLite3.py
pOrgz/commons/__init__.py
pOrgz/commons/_primitiveQueries.py
pOrgz/core/__init__.py
pOrgz/exceptions/__init__.py
pOrgz/libs/__init__.py
pOrgz-0.0.2.dist-info/LICENSE
pOrgz-0.0.2.dist-info/METADATA
pOrgz-0.0.2.dist-info/WHEEL
pOrgz-0.0.2.dist-info/top_level.txt
pOrgz-0.0.2.dist-info/RECORD
