Metadata-Version: 2.1
Name: pOrgz
Version: 0.0.2
Summary: A Financial Organizer and Predictor
Home-page: https://github.com/pOrgz/pOrgz-py
Author: Debmalya Pramanik
Author-email: 
License: UNKNOWN
Platform: UNKNOWN
Classifier: Programming Language :: Python :: 3
Classifier: License :: OSI Approved :: MIT License
Requires-Python: >=3.6
Requires-Dist: numpy
